[{
  "_id": {
    "$oid": "64e5287f447014b03ced8675"
  },
  "id_order": 1,
  "location": "Dirección 123",
  "distance_in_km": 5.2,
  "estimated_time": "30 minutos",
  "total": "42.50$",
  "city": "Ciudad A",
  "driver": "1"
},
{
  "_id": {
    "$oid": "64e5287f447014b03ced8676"
  },
  "id_order": 2,
  "location": "Dirección 456",
  "distance_in_km": 8.7,
  "estimated_time": "45 minutos",
  "total": "29.99$",
  "city": "Ciudad B",
  "driver": "2"
},
{
  "_id": {
    "$oid": "64e5287f447014b03ced8677"
  },
  "id_order": 3,
  "location": "Dirección 789",
  "distance_in_km": 3,
  "estimated_time": "20 minutos",
  "total": "15.75$",
  "city": "Ciudad C",
  "driver": "3"
},
{
  "_id": {
    "$oid": "64e5287f447014b03ced8678"
  },
  "id_order": 4,
  "location": "Dirección 101",
  "distance_in_km": 6.5,
  "estimated_time": "35 minutos",
  "total": "50.00$",
  "city": "Ciudad A",
  "driver": "4"
},
{
  "_id": {
    "$oid": "64e5287f447014b03ced8679"
  },
  "id_order": 5,
  "location": "Dirección 202",
  "distance_in_km": 4.1,
  "estimated_time": "25 minutos",
  "total": "18.95$",
  "city": "Ciudad B",
  "driver": "5"
},
{
  "_id": {
    "$oid": "64e5287f447014b03ced867a"
  },
  "id_order": 6,
  "location": "Dirección 303",
  "distance_in_km": 7.8,
  "estimated_time": "40 minutos",
  "total": "35.25$",
  "city": "Ciudad C",
  "driver": "6"
},
{
  "_id": {
    "$oid": "64e5287f447014b03ced867b"
  },
  "id_order": 7,
  "location": "Dirección 404",
  "distance_in_km": 2.5,
  "estimated_time": "15 minutos",
  "total": "10.50$",
  "city": "Ciudad A",
  "driver": "7"
},
{
  "_id": {
    "$oid": "64e5287f447014b03ced867c"
  },
  "id_order": 8,
  "location": "Dirección 505",
  "distance_in_km": 9.3,
  "estimated_time": "50 minutos",
  "total": "62.75$",
  "city": "Ciudad B",
  "driver": "8"
},
{
  "_id": {
    "$oid": "64e5287f447014b03ced867d"
  },
  "id_order": 9,
  "location": "Dirección 606",
  "distance_in_km": 3.8,
  "estimated_time": "23 minutos",
  "total": "21.00$",
  "city": "Ciudad C",
  "driver": "9"
},
{
  "_id": {
    "$oid": "64e5287f447014b03ced867e"
  },
  "id_order": 10,
  "location": "Dirección 707",
  "distance_in_km": 5,
  "estimated_time": "30 minutos",
  "total": "38.50$",
  "city": "Ciudad A",
  "driver": "10"
},
{
  "_id": {
    "$oid": "64e5287f447014b03ced867f"
  },
  "id_order": 11,
  "location": "Dirección 808",
  "distance_in_km": 7.1,
  "estimated_time": "42 minutos",
  "total": "27.80$",
  "city": "Ciudad B",
  "driver": "1"
},
{
  "_id": {
    "$oid": "64e5287f447014b03ced8680"
  },
  "id_order": 12,
  "location": "Dirección 909",
  "distance_in_km": 4.9,
  "estimated_time": "28 minutos",
  "total": "13.25$",
  "city": "Ciudad C",
  "driver": "2"
},
{
  "_id": {
    "$oid": "64e5287f447014b03ced8681"
  },
  "id_order": 13,
  "location": "Dirección 1010",
  "distance_in_km": 6,
  "estimated_time": "35 minutos",
  "total": "45.60$",
  "city": "Ciudad A",
  "driver": "3"
},
{
  "_id": {
    "$oid": "64e5287f447014b03ced8682"
  },
  "id_order": 14,
  "location": "Dirección 1111",
  "distance_in_km": 3.3,
  "estimated_time": "18 minutos",
  "total": "16.99$",
  "city": "Ciudad B",
  "driver": "4"
},
{
  "_id": {
    "$oid": "64e5287f447014b03ced8683"
  },
  "id_order": 15,
  "location": "Dirección 1212",
  "distance_in_km": 8,
  "estimated_time": "48 minutos",
  "total": "30.75$",
  "city": "Ciudad C",
  "driver": "5"
},
{
  "_id": {
    "$oid": "64e7a4e8f2a8ee7db0c7aa76"
  },
  "id_order": 16,
  "location": "Dirección 1212",
  "distance_in_km": "8",
  "estimated_time": "48 minutos",
  "total": "35.75$",
  "city": "Ciudad C",
  "driver": "6",
  "__v": 0
},
{
  "_id": {
    "$oid": "64e7a5dcf2a8ee7db0c7aa7f"
  },
  "id_order": 17,
  "location": "Dirección 1213",
  "distance_in_km": "8",
  "estimated_time": "48 minutos",
  "total": "45.75$",
  "city": "Ciudad C",
  "driver": "3",
  "__v": 0
},
{
  "_id": {
    "$oid": "64eae01e6e7bb4fd671e8af2"
  },
  "id_order": 18,
  "location": "policarpo paz garcia",
  "distance_in_km": "25km",
  "estimated_time": "2:00 hr",
  "total": "125$",
  "city": "tegucigalpa",
  "driver": "13",
  "__v": 0
}]